{
  "timestamp": "2025-10-17T14:13:21.335Z",
  "modules": {
    "auth": {
      "status": "issues",
      "foundFiles": 1,
      "totalFiles": 4,
      "hasErrors": true,
      "cssIssues": 0,
      "timestamp": "2025-10-17T14:12:54.693Z"
    },
    "dashboard": {
      "status": "issues",
      "foundFiles": 1,
      "totalFiles": 4,
      "hasErrors": true,
      "cssIssues": 0,
      "timestamp": "2025-10-17T14:12:59.005Z"
    },
    "admin": {
      "status": "issues",
      "foundFiles": 1,
      "totalFiles": 4,
      "hasErrors": true,
      "cssIssues": 0,
      "timestamp": "2025-10-17T14:12:59.174Z"
    },
    "doctor": {
      "status": "issues",
      "foundFiles": 0,
      "totalFiles": 4,
      "hasErrors": true,
      "cssIssues": 0,
      "timestamp": "2025-10-17T14:12:59.332Z"
    },
    "staff": {
      "status": "issues",
      "foundFiles": 0,
      "totalFiles": 4,
      "hasErrors": true,
      "cssIssues": 0,
      "timestamp": "2025-10-17T14:12:59.489Z"
    },
    "supervisor": {
      "status": "issues",
      "foundFiles": 0,
      "totalFiles": 4,
      "hasErrors": true,
      "cssIssues": 0,
      "timestamp": "2025-10-17T14:12:59.648Z"
    },
    "patient": {
      "status": "issues",
      "foundFiles": 0,
      "totalFiles": 4,
      "hasErrors": true,
      "cssIssues": 0,
      "timestamp": "2025-10-17T14:12:59.807Z"
    },
    "api": {
      "status": "issues",
      "foundFiles": 0,
      "totalFiles": 4,
      "hasErrors": true,
      "cssIssues": 0,
      "timestamp": "2025-10-17T14:13:02.929Z"
    },
    "components": {
      "status": "issues",
      "foundFiles": 0,
      "totalFiles": 4,
      "hasErrors": true,
      "cssIssues": 0,
      "timestamp": "2025-10-17T14:13:09.793Z"
    },
    "hooks": {
      "status": "issues",
      "foundFiles": 0,
      "totalFiles": 4,
      "hasErrors": true,
      "cssIssues": 0,
      "timestamp": "2025-10-17T14:13:12.331Z"
    },
    "lib": {
      "status": "issues",
      "foundFiles": 0,
      "totalFiles": 4,
      "hasErrors": true,
      "cssIssues": 0,
      "timestamp": "2025-10-17T14:13:16.310Z"
    },
    "styles": {
      "status": "issues",
      "foundFiles": 0,
      "totalFiles": 4,
      "hasErrors": true,
      "cssIssues": 0,
      "timestamp": "2025-10-17T14:13:18.809Z"
    },
    "context": {
      "status": "issues",
      "foundFiles": 0,
      "totalFiles": 4,
      "hasErrors": true,
      "cssIssues": 0,
      "timestamp": "2025-10-17T14:13:21.335Z"
    }
  },
  "summary": {
    "total": 13,
    "healthy": 0,
    "issues": 13,
    "missing": 0,
    "errors": 0
  }
}